{"time": "Wed Nov 17 16:00:03 2021", "data": [{"t1": "21", "w1": "#covid19", "t2": "14", "w2": "#covid_19", "t3": "5", "w3": "#pfizer", "t4": "4", "w4": "#4tdestruyeamexico", "t5": "2", "w5": "#nobajemoslaguardia", "t6": "2", "w6": "#ultimahora", "t7": "2", "w7": "#saludsonora", "t8": "2", "w8": "#quedateencasa", "t9": "2", "w9": "#vacunacion", "t10": "2", "w10": "#vacunacovid19", "t11": "2", "w11": "#ticul", "t12": "2", "w12": "#salud", "t13": "1", "w13": "#jalisco", "t14": "1", "w14": "#coronavirus", "t15": "1", "w15": "#michaelbuble", "t16": "1", "w16": "#higiene", "t17": "1", "w17": "#primeraemision", "t18": "1", "w18": "#tresminutosdeoracion", "t19": "1", "w19": "#covid", "t20": "1", "w20": "#alergia", "t21": "1", "w21": "#alergias", "t22": "1", "w22": "#monterrey", "t23": "1", "w23": "#aviso", "t24": "1", "w24": "#importante", "t25": "1", "w25": "#19nov", "t26": "1", "w26": "#hugolopezgatell", "t27": "1", "w27": "#encasa", "t28": "1", "w28": "#aniversario", "t29": "1", "w29": "#2013-2021", "t30": "1", "w30": "#influenza", "t31": "1", "w31": "#ofiolanuevanormalidad", "t32": "1", "w32": "#almomento", "t33": "1", "w33": "#uaq", "t34": "1", "w34": "#\ud835\udc34\ud835\udc5a", "t35": "1", "w35": "#\ud835\udc38\ud835\udc60\ud835\udc3f\ud835\udc4e\ud835\udc42\ud835\udc5b\ud835\udc51\ud835\udc4e\ud835\udc46\ud835\udc52\ud835\udc5f\ud835\udc41\ud835\udc56\ud835\udc5b\u0303\ud835\udc5c", "t36": "1", "w36": "#hambre", "t37": "1", "w37": "#frio", "t38": "1", "w38": "#pandemia", "t39": "1", "w39": "#falta", "t40": "1", "w40": "#empleos", "t41": "1", "w41": "#educacion", "t42": "1", "w42": "#pef2022", "t43": "1", "w43": "#vacunacontraelcovid19", "t44": "1", "w44": "#sinovac", "t45": "1", "w45": "#marthavila", "t46": "1", "w46": "#esposa", "t47": "1", "w47": "#claudiosanchezislas", "t48": "1", "w48": "#hemeroteca", "t49": "1", "w49": "#depandemia", "t50": "1", "w50": "#cuadernos", "t51": "1", "w51": "#ricardomoralesmiranda", "t52": "1", "w52": "#income", "t53": "1", "w53": "#workfromhome", "t54": "1", "w54": "#saludmental", "t55": "1", "w55": "#saludintegral", "t56": "1", "w56": "#prevenciondelsuicidio", "t57": "1", "w57": "#motivacion", "t58": "1", "w58": "#autoestima", "t59": "1", "w59": "#ansiedad", "t60": "1", "w60": "#procesospersonales", "t61": "1", "w61": "#viernes19", "t62": "1", "w62": "#mexicanos", "t63": "1", "w63": "#ligadeguerreros", "t64": "1", "w64": "#yomevacuno", "t65": "1", "w65": "#pobreza", "t66": "1", "w66": "#desigualdad", "t67": "1", "w67": "#recuperacion", "t68": "1", "w68": "#colmex", "t69": "1", "w69": "#somostucruzroja", "t70": "1", "w70": "#fletesytrasladosdelgado", "t71": "1", "w71": "#fletes", "t72": "1", "w72": "#mudanza", "t73": "1", "w73": "#jpenformula", "t74": "1", "w74": "#merida", "t75": "1", "w75": "#sanluispotosi", "t76": "1", "w76": "#34", "t77": "1", "w77": "#saltillo", "t78": "1", "w78": "#noticiaalmomento", "t79": "1", "w79": "#tudiariovivir", "t80": "1", "w80": "#corsirosenthalbox", "t81": "1", "w81": "#covidisairborne", "t82": "1", "w82": "#vacunaparatodxs", "t83": "1", "w83": "#vacunaparaadolescentes", "t84": "1", "w84": "#actualizacion", "t85": "1", "w85": "#nuevoleon", "t86": "1", "w86": "#orgulloibero", "t87": "1", "w87": "#enterate", "t88": "1", "w88": "#vacunacioncovid19", "t89": "1", "w89": "#doctorencasa", "t90": "1", "w90": "#europa", "t91": "1", "w91": "#austria", "t92": "1", "w92": "#elcurandero13", "t93": "1", "w93": "#diamundialdeladiabetes", "t94": "1", "w94": "#wdd", "t95": "1", "w95": "#dmd", "t96": "1", "w96": "#sinoahoracuando", "t97": "1", "w97": "#cuidatucorazon", "t98": "1", "w98": "#nicolasromero", "t99": "1", "w99": "#regionlaguna", "t100": "1", "w100": "#coahuila", "t101": "1", "w101": "#infame", "t102": "1", "w102": "#noseanasiplebes", "t103": "1", "w103": "#nacional", "t104": "1", "w104": "#panoramacovid\ud83d\udfe2", "t105": "1", "w105": "#morelos", "t106": "1", "w106": "#sanadistancia", "t107": "1", "w107": "#usacubrebocas", "t108": "1", "w108": "#lavadodemanos", "t109": "1", "w109": "#noti13", "t110": "1", "w110": "#san", "t111": "1", "w111": "#cdmx", "t112": "1", "w112": "#comparecencias2021"}, {"t1": "6", "w1": "@hlgatell", "t2": "5", "w2": "@lopezobrador", "t3": "3", "w3": "@ssalud_mx", "t4": "3", "w4": "@banorte_mx", "t5": "3", "w5": "@sororavirus", "t6": "3", "w6": "@tu_imss", "t7": "2", "w7": "@acereros", "t8": "2", "w8": "@doctormacias", "t9": "2", "w9": "@patyarmendariz", "t10": "2", "w10": "@lialimon", "t11": "2", "w11": "@laurorodriguez", "t12": "2", "w12": "@ntrguadalajara", "t13": "2", "w13": "@pfizermx", "t14": "2", "w14": "@andreq22903705", "t15": "2", "w15": "@rosscitalan", "t16": "2", "w16": "@sandralopezleon", "t17": "2", "w17": "@issste_mx", "t18": "2", "w18": "@insabi_mx", "t19": "1", "w19": "@emeequis", "t20": "1", "w20": "@marcelasaebl", "t21": "1", "w21": "@saruchango", "t22": "1", "w22": "@keniaconilatina", "t23": "1", "w23": "@viajavolaris", "t24": "1", "w24": "@profeco", "t25": "1", "w25": "@gavinci7", "t26": "1", "w26": "@yosoycastrillon", "t27": "1", "w27": "@agencia_vn", "t28": "1", "w28": "@arturocarlos", "t29": "1", "w29": "@cadenajovenmx", "t30": "1", "w30": "@cadenaradiomx", "t31": "1", "w31": "@manadapolitica", "t32": "1", "w32": "@mattb_2013", "t33": "1", "w33": "@jacobdrj", "t34": "1", "w34": "@georgetakei", "t35": "1", "w35": "@untalaxis", "t36": "1", "w36": "@sacmexcdmx", "t37": "1", "w37": "@alcaldiaao", "t38": "1", "w38": "@vecinos_aob", "t39": "1", "w39": "@carlosflores_78", "t40": "1", "w40": "@la_bellackit4", "t41": "1", "w41": "@sipsenoticiastv", "t42": "1", "w42": "@sipsetv", "t43": "1", "w43": "@mtyfollowmx", "t44": "1", "w44": "@asiesmonterrey", "t45": "1", "w45": "@like_mty", "t46": "1", "w46": "@mty_leones", "t47": "1", "w47": "@cicmty", "t48": "1", "w48": "@drchavezdiaz", "t49": "1", "w49": "@excelsior", "t50": "1", "w50": "@cartoncalderon", "t51": "1", "w51": "@cdcgov", "t52": "1", "w52": "@alfredoair23", "t53": "1", "w53": "@revistamassana", "t54": "1", "w54": "@cothtwit", "t55": "1", "w55": "@katieappleseed7", "t56": "1", "w56": "@arturo_rdz16", "t57": "1", "w57": "@sonia_ssi", "t58": "1", "w58": "@elgatopolitico", "t59": "1", "w59": "@lopezdoriga", "t60": "1", "w60": "@carmelodifazio", "t61": "1", "w61": "@cemees_org", "t62": "1", "w62": "@bicivilizados", "t63": "1", "w63": "@arabonita", "t64": "1", "w64": "@capitanporfirio", "t65": "1", "w65": "@djny", "t66": "1", "w66": "@reuters", "t67": "1", "w67": "@rutilioescandon", "t68": "1", "w68": "@humbertcarrasco", "t69": "1", "w69": "@mazacuato", "t70": "1", "w70": "@angelika8882", "t71": "1", "w71": "@fvazqpen", "t72": "1", "w72": "@medinagual", "t73": "1", "w73": "@cimenna", "t74": "1", "w74": "@educacionibero", "t75": "1", "w75": "@mariocoan", "t76": "1", "w76": "@dreamfieldsfest", "t77": "1", "w77": "@maximoavance", "t78": "1", "w78": "@nfl", "t79": "1", "w79": "@steelers", "t80": "1", "w80": "@pfizer", "t81": "1", "w81": "@diariodeunloc0", "t82": "1", "w82": "@siempremonro", "t83": "1", "w83": "@sanch6899", "t84": "1", "w84": "@cnnee", "t85": "1", "w85": "@fraluna1109", "t86": "1", "w86": "@superchesse", "t87": "1", "w87": "@oscar_floch", "t88": "1", "w88": "@analeonorespino", "t89": "1", "w89": "@drpacomoreno1", "t90": "1", "w90": "@enriquesnyder", "t91": "1", "w91": "@adrianaxto", "t92": "1", "w92": "@jannet_lp", "t93": "1", "w93": "@28maeta", "t94": "1", "w94": "@sugeyabrego", "t95": "1", "w95": "@danielapastrana", "t96": "1", "w96": "@jse922", "t97": "1", "w97": "@matthewfairburn", "t98": "1", "w98": "@zoerobledo", "t99": "1", "w99": "@almarosamarroq2", "t100": "1", "w100": "@nlsalud", "t101": "1", "w101": "@denisedresserg", "t102": "1", "w102": "@paqmoreno", "t103": "1", "w103": "@ivanrocharodelo", "t104": "1", "w104": "@senadomexicano", "t105": "1", "w105": "@mx_diputados", "t106": "1", "w106": "@ibreen_jav", "t107": "1", "w107": "@beautyofertasmx", "t108": "1", "w108": "@saludedomex", "t109": "1", "w109": "@gobcdmx"}, {"t1": "49", "w1": "pandemia", "t2": "29", "w2": "a\u00f1os", "t3": "26", "w3": "\ud83d\udea8", "t4": "17", "w4": "pildora", "t5": "16", "w5": "salud", "t6": "15", "w6": "mexico", "t7": "14", "w7": "virus", "t8": "13", "w8": "viernes", "t9": "13", "w9": "\ud83e\udd23", "t10": "12", "w10": "meses", "t11": "12", "w11": "adolescentes", "t12": "12", "w12": "comorbilidades", "t13": "12", "w13": "noviembre", "t14": "12", "w14": "acuerdo", "t15": "11", "w15": "patente", "t16": "10", "w16": "dosis", "t17": "10", "w17": "partir", "t18": "10", "w18": "pfizer", "t19": "10", "w19": "firma", "t20": "9", "w20": "vacuna", "t21": "8", "w21": "manejo", "t22": "7", "w22": "despues", "t23": "7", "w23": "personas", "t24": "7", "w24": "vacunacion", "t25": "7", "w25": "menores", "t26": "7", "w26": "primera", "t27": "6", "w27": "casos", "t28": "6", "w28": "dia", "t29": "6", "w29": "a\u00f1o", "t30": "6", "w30": "jovenes", "t31": "6", "w31": "pre-registro", "t32": "5", "w32": "defunciones", "t33": "5", "w33": "cosas", "t34": "5", "w34": "sintomas", "t35": "5", "w35": "paises", "t36": "5", "w36": "casa", "t37": "5", "w37": "atencion", "t38": "5", "w38": "prueba", "t39": "4", "w39": "fin", "t40": "4", "w40": "bueno", "t41": "4", "w41": "mundo", "t42": "4", "w42": "cubrebocas", "t43": "4", "w43": "peor", "t44": "4", "w44": "covid19", "t45": "4", "w45": "mexicanos", "t46": "4", "w46": "inicio", "t47": "4", "w47": "subsecretario", "t48": "4", "w48": "registro", "t49": "4", "w49": "edad", "t50": "4", "w50": "gobierno", "t51": "4", "w51": "conmorbilidades", "t52": "4", "w52": "licencia", "t53": "4", "w53": "prerregistro", "t54": "4", "w54": "sintoma", "t55": "4", "w55": "\ud83c\udffb", "t56": "4", "w56": "vez", "t57": "4", "w57": "centro", "t58": "3", "w58": "crisis", "t59": "3", "w59": "sanitaria", "t60": "3", "w60": "amigos", "t61": "3", "w61": "problemas", "t62": "3", "w62": "serio", "t63": "3", "w63": "enfermedad", "t64": "3", "w64": "pacientes", "t65": "3", "w65": "enfermedades", "t66": "3", "w66": "sea", "t67": "3", "w67": "proximo", "t68": "3", "w68": "solo", "t69": "3", "w69": "calle", "t70": "3", "w70": "\ud83d\ude02", "t71": "3", "w71": "influenza", "t72": "3", "w72": "tambien", "t73": "3", "w73": "anillo", "t74": "3", "w74": "dedo", "t75": "3", "w75": "dias", "t76": "3", "w76": "\ud83e\udd72", "t77": "3", "w77": "buenos", "t78": "3", "w78": "buen", "t79": "3", "w79": "martes", "t80": "3", "w80": "acceso", "t81": "3", "w81": "mundial", "t82": "3", "w82": "anticovid", "t83": "3", "w83": "muerte", "t84": "3", "w84": "global", "t85": "3", "w85": "antiviral", "t86": "3", "w86": "padres", "t87": "3", "w87": "familia", "t88": "3", "w88": "educacion", "t89": "3", "w89": "sanitarias", "t90": "3", "w90": "clinica", "t91": "3", "w91": "forma", "t92": "3", "w92": "autoridades", "t93": "3", "w93": "plataforma", "t94": "3", "w94": "experimental", "t95": "3", "w95": "\ud83d\udc89", "t96": "3", "w96": "contagios", "t97": "3", "w97": "nuevos", "t98": "3", "w98": "poblacion", "t99": "2", "w99": "gran", "t100": "2", "w100": "mas", "t101": "2", "w101": "inseguridad", "t102": "2", "w102": "pobreza", "t103": "2", "w103": "estado", "t104": "2", "w104": "piedras", "t105": "2", "w105": "ingreso", "t106": "2", "w106": "tiempos", "t107": "2", "w107": "vacunados", "t108": "2", "w108": "vs", "t109": "2", "w109": "tiempo", "t110": "2", "w110": "vacunadas", "t111": "2", "w111": "credito", "t112": "2", "w112": "prorroga", "t113": "2", "w113": "cuidado", "t114": "2", "w114": "paso", "t115": "2", "w115": "huarache", "t116": "2", "w116": "uso", "t117": "2", "w117": "certificado", "t118": "2", "w118": "ideas", "t119": "2", "w119": "ignorantes", "t120": "2", "w120": "pais", "t121": "2", "w121": "ultima", "t122": "2", "w122": "ola", "t123": "2", "w123": "respiratorias", "t124": "2", "w124": "caso", "t125": "2", "w125": "falta", "t126": "2", "w126": "chips", "t127": "2", "w127": "ojos", "t128": "2", "w128": "rezagados", "t129": "2", "w129": "grandes", "t130": "2", "w130": "ma\u00f1ana", "t131": "2", "w131": "redes", "t132": "2", "w132": "pregunta", "t133": "2", "w133": "gracias", "t134": "2", "w134": "lunes", "t135": "2", "w135": "jurisdiccion", "t136": "2", "w136": "enfermos", "t137": "2", "w137": "fallecidos", "t138": "2", "w138": "trabajadores", "t139": "2", "w139": "alergia", "t140": "2", "w140": "covid-19", "t141": "2", "w141": "ni\u00f1os", "t142": "2", "w142": "preregistro", "t143": "2", "w143": "pesimo", "t144": "2", "w144": "funcionarios", "t145": "2", "w145": "mediocres", "t146": "2", "w146": "datos", "t147": "2", "w147": "noticia", "t148": "2", "w148": "millones", "t149": "2", "w149": "pesos", "t150": "2", "w150": "materia", "t151": "2", "w151": "amplio", "t152": "2", "w152": "fabricantes", "t153": "2", "w153": "genericos", "t154": "2", "w154": "disponible", "t155": "2", "w155": "ingresos", "t156": "2", "w156": "bajos", "t157": "2", "w157": "medios", "t158": "2", "w158": "hijos", "t159": "2", "w159": "\u201d", "t160": "2", "w160": "prevencion", "t161": "2", "w161": "\u2764", "t162": "2", "w162": "federal", "t163": "2", "w163": "medidas", "t164": "2", "w164": "pef", "t165": "2", "w165": "servicios", "t166": "2", "w166": "general", "t167": "2", "w167": "sabado", "t168": "2", "w168": "se\u00f1ora", "t169": "2", "w169": "presidente", "t170": "2", "w170": "corrupcion", "t171": "2", "w171": "live", "t172": "2", "w172": "their", "t173": "2", "w173": "have", "t174": "2", "w174": "reactivacion", "t175": "2", "w175": "proceso", "t176": "2", "w176": "px", "t177": "2", "w177": "segundo", "t178": "2", "w178": "tema", "t179": "2", "w179": "miedo", "t180": "2", "w180": "vacunas", "t181": "2", "w181": "ansiedad", "t182": "2", "w182": "trabajo", "t183": "2", "w183": "terrible", "t184": "2", "w184": "parte", "t185": "2", "w185": "hora", "t186": "2", "w186": "buena", "t187": "2", "w187": "sigamos", "t188": "2", "w188": "veces", "t189": "2", "w189": "informacion", "t190": "2", "w190": "llamada", "t191": "2", "w191": "pruebas", "t192": "2", "w192": "equipo", "t193": "2", "w193": "investigacion", "t194": "2", "w194": "pobres", "t195": "2", "w195": "generico", "t196": "2", "w196": "anti-covid", "t197": "2", "w197": "tos", "t198": "2", "w198": "astrazeneca", "t199": "2", "w199": "delegacion", "t200": "2", "w200": "contactos", "t201": "2", "w201": "encierro", "t202": "2", "w202": "anti", "t203": "2", "w203": "amor", "t204": "2", "w204": "grupo", "t205": "2", "w205": "fotos", "t206": "2", "w206": "recuerdos", "t207": "2", "w207": "festival", "t208": "2", "w208": "peligroso", "t209": "2", "w209": "vidas", "t210": "2", "w210": "tierra", "t211": "2", "w211": "secretaria", "t212": "2", "w212": "antivirus", "t213": "2", "w213": "vida", "t214": "2", "w214": "meteoro", "t215": "2", "w215": "rehabilitacion", "t216": "2", "w216": "secuelas", "t217": "2", "w217": "igual", "t218": "2", "w218": "segunda", "t219": "2", "w219": "octubre", "t220": "1", "w220": "gusto", "t221": "1", "w221": "ingeniero", "t222": "1", "w222": "montes", "t223": "1", "w223": "platicamos", "t224": "1", "w224": "dificultades", "t225": "1", "w225": "economicas", "t226": "1", "w226": "significo", "t227": "1", "w227": "sector", "t228": "1", "w228": "privado", "t229": "1", "w229": "afronto", "t230": "1", "w230": "enriquecedor", "t231": "1", "w231": "punto", "t232": "1", "w232": "vista", "t233": "1", "w233": "consejo", "t234": "1", "w234": "cifras", "t235": "1", "w235": "activos", "t236": "1", "w236": "estimados", "t237": "1", "w237": "recuperadas", "t238": "1", "w238": "osito", "t239": "1", "w239": "inmunocall", "t240": "1", "w240": "pelo", "t241": "1", "w241": "inminentes", "t242": "1", "w242": "chairiza", "t243": "1", "w243": "ademas", "t244": "1", "w244": "permiso", "t245": "1", "w245": "imposible", "t246": "1", "w246": "instituto", "t247": "1", "w247": "directivos", "t248": "1", "w248": "recomendado", "t249": "1", "w249": "pielonefritis", "t250": "1", "w250": "pulmon", "t251": "1", "w251": "principios", "t252": "1", "w252": "asma", "t253": "1", "w253": "big", "t254": "1", "w254": "reserve", "t255": "1", "w255": "entrenamientos", "t256": "1", "w256": "starter", "t257": "1", "w257": "rudolph", "t258": "1", "w258": "pijama", "t259": "1", "w259": "pleno", "t260": "1", "w260": "sol", "t261": "1", "w261": "raros", "t262": "1", "w262": "videollamada", "t263": "1", "w263": "posible", "t264": "1", "w264": "date", "t265": "1", "w265": "trastes", "t266": "1", "w266": "lloro", "t267": "1", "w267": "aventho", "t268": "1", "w268": "colegio", "t269": "1", "w269": "bien", "t270": "1", "w270": "cuanto", "t271": "1", "w271": "aplica", "t272": "1", "w272": "confinamiento", "t273": "1", "w273": "seguro", "t274": "1", "w274": "viej4", "t275": "1", "w275": "pzifer", "t276": "1", "w276": "salio", "t277": "1", "w277": "laredo", "t278": "1", "w278": "via", "t279": "1", "w279": "concierto", "t280": "1", "w280": "final", "t281": "1", "w281": "cancelo", "t282": "1", "w282": "\ud83e\udd75", "t283": "1", "w283": "comision", "t284": "1", "w284": "ciudadana", "t285": "1", "w285": "mes", "t286": "1", "w286": "rezagos", "t287": "1", "w287": "laguna", "t288": "1", "w288": "times", "t289": "1", "w289": "without", "t290": "1", "w290": "that", "t291": "1", "w291": "encerrado", "t292": "1", "w292": "\u2026", "t293": "1", "w293": "huevos", "t294": "1", "w294": "suministro", "t295": "1", "w295": "agua", "t296": "1", "w296": "potable", "t297": "1", "w297": "molino", "t298": "1", "w298": "santo", "t299": "1", "w299": "domingo", "t300": "1", "w300": "mayoria", "t301": "1", "w301": "menor", "t302": "1", "w302": "bacterias", "t303": "1", "w303": "es", "t304": "1", "w304": "decir", "t305": "1", "w305": "estes", "t306": "1", "w306": "descalzo", "t307": "1", "w307": "moraleja", "t308": "1", "w308": "rasgados", "t309": "1", "w309": "escoria", "t310": "1", "w310": "planeta", "t311": "1", "w311": "cucus", "t312": "1", "w312": "nuevas", "t313": "1", "w313": "fechas", "t314": "1", "w314": "subject", "t315": "1", "w315": "and", "t316": "1", "w316": "persecution", "t317": "1", "w317": "sarscov2", "t318": "1", "w318": "espacios", "t319": "1", "w319": "cerrados", "t320": "1", "w320": "aglomeraciones", "t321": "1", "w321": "muertos", "t322": "1", "w322": "violencia", "t323": "1", "w323": "millon", "t324": "1", "w324": "parques", "t325": "1", "w325": "narcomenudeo", "t326": "1", "w326": "inteligente", "t327": "1", "w327": "se\u00f1al", "t328": "1", "w328": "semana", "t329": "1", "w329": "laboral", "t330": "1", "w330": "regreso", "t331": "1", "w331": "excelente", "t332": "1", "w332": "google", "t333": "1", "w333": "maps", "t334": "1", "w334": "filtro", "t335": "1", "w335": "epidemia", "t336": "1", "w336": "alza", "t337": "1", "w337": "cara", "t338": "1", "w338": "toluca", "t339": "1", "w339": "sanos", "t340": "1", "w340": "comezon", "t341": "1", "w341": "nariz", "t342": "1", "w342": "garganta", "t343": "1", "w343": "estornudos", "t344": "1", "w344": "escurrimiento", "t345": "1", "w345": "congestion", "t346": "1", "w346": "nasal", "t347": "1", "w347": "-le", "t348": "1", "w348": "juro", "t349": "1", "w349": "portada", "t350": "1", "w350": "expansion", "t351": "1", "w351": "food", "t352": "1", "w352": "tech", "t353": "1", "w353": "ni\u00f1as", "t354": "1", "w354": "anuncio", "t355": "1", "w355": "pagina", "t356": "1", "w356": "menciono", "t357": "1", "w357": "manipulados", "t358": "1", "w358": "triste", "t359": "1", "w359": "medicamento", "t360": "1", "w360": "subejercicio", "t361": "1", "w361": "medio", "t362": "1", "w362": "mira", "t363": "1", "w363": "oliva", "t364": "1", "w364": "congreso", "t365": "1", "w365": "facil", "t366": "1", "w366": "taquillero", "t367": "1", "w367": "culpa", "t368": "1", "w368": "mal", "t369": "1", "w369": "coresponsables", "t370": "1", "w370": "luces", "t371": "1", "w371": "papas", "t372": "1", "w372": "plantel", "t373": "1", "w373": "encerrados", "t374": "1", "w374": "localidad", "t375": "1", "w375": "bastandonos", "t376": "1", "w376": "participacion", "t377": "1", "w377": "extranjera", "t378": "1", "w378": "s.", "t379": "1", "w379": "xix", "t380": "1", "w380": "cubreboca", "t381": "1", "w381": "lloradita", "t382": "1", "w382": "gimnasio", "t383": "1", "w383": "cosa", "t384": "1", "w384": "positiva", "t385": "1", "w385": "promocion", "t386": "1", "w386": "todavia", "t387": "1", "w387": "conferencia", "t388": "1", "w388": "prensa", "t389": "1", "w389": "matutina", "t390": "1", "w390": "2021", "t391": "1", "w391": "ultimo", "t392": "1", "w392": "feliz", "t393": "1", "w393": "adicionales", "t394": "1", "w394": "doctor", "t395": "1", "w395": "tips", "t396": "1", "w396": "aderezada", "t397": "1", "w397": "patent", "t398": "1", "w398": "it's", "t399": "1", "w399": "tributo", "t400": "1", "w400": "chaqueton", "t401": "1", "w401": "frio", "t402": "1", "w402": "informes", "t403": "1", "w403": "inbox", "t404": "1", "w404": "programas", "t405": "1", "w405": "recorte", "t406": "1", "w406": "anual", "t407": "1", "w407": "verdadero", "t408": "1", "w408": "santa", "t409": "1", "w409": "medicina", "t410": "1", "w410": "especialidades", "t411": "1", "w411": "pm", "t412": "1", "w412": "lt;despues", "t413": "1", "w413": "\ufe0f", "t414": "1", "w414": "aceitunas", "t415": "1", "w415": "nervios", "t416": "1", "w416": "infeccion", "t417": "1", "w417": "\u24d8", "t418": "1", "w418": "hijo", "t419": "1", "w419": "pesadilla", "t420": "1", "w420": "\u201c", "t421": "1", "w421": "cibernetico", "t422": "1", "w422": "exclamo", "t423": "1", "w423": "cautela", "t424": "1", "w424": "dispositivo", "t425": "1", "w425": "vivienda", "t426": "1", "w426": "necesidades", "t427": "1", "w427": "pueblo", "t428": "1", "w428": "mexicano", "t429": "1", "w429": "aprobacion", "t430": "1", "w430": "delincuencia", "t431": "1", "w431": "dec", "t432": "1", "w432": "when", "t433": "1", "w433": "hospitalization", "t434": "1", "w434": "situation", "t435": "1", "w435": "normal", "t436": "1", "w436": "inversiones", "t437": "1", "w437": "turismo|", "t438": "1", "w438": "\u2066@torrucoturismo", "t439": "1", "w439": "\u2069", "t440": "1", "w440": "socio", "t441": "1", "w441": "\u2066@isidoroyescas\u2069", "t442": "1", "w442": "critico", "t443": "1", "w443": "canula", "t444": "1", "w444": "traqueos", "t445": "1", "w445": "extra", "t446": "1", "w446": "\ud83c\uddf8", "t447": "1", "w447": "capitulo", "t448": "1", "w448": "podcast", "t449": "1", "w449": "olas", "t450": "1", "w450": "cafe", "t451": "1", "w451": "feminismo", "t452": "1", "w452": "gobernantes", "t453": "1", "w453": "reflejos", "t454": "1", "w454": "rapidos", "t455": "1", "w455": "contingencia", "t456": "1", "w456": "mauricio", "t457": "1", "w457": "sociales", "t458": "1", "w458": "verdad", "t459": "1", "w459": "importantes", "t460": "1", "w460": "unico", "t461": "1", "w461": "argumento", "t462": "1", "w462": "gif", "t463": "1", "w463": "profunda", "t464": "1", "w464": "ignorancia", "t465": "1", "w465": "vecinos", "t466": "1", "w466": "suficientes", "t467": "1", "w467": "economia", "t468": "1", "w468": "estable", "t469": "1", "w469": "digna", "t470": "1", "w470": "detectas", "t471": "1", "w471": "dejes", "t472": "1", "w472": "dudas", "t473": "1", "w473": "minuto", "t474": "1", "w474": "primer", "t475": "1", "w475": "podria", "t476": "1", "w476": "contento", "t477": "1", "w477": "lugar", "t478": "1", "w478": "totalidad", "t479": "1", "w479": "rostro", "t480": "1", "w480": "portal", "t481": "1", "w481": "imagen", "t482": "1", "w482": "eficiente", "t483": "1", "w483": "empleados", "t484": "1", "w484": "alcaldia", "t485": "1", "w485": "semaforo", "t486": "1", "w486": "verde", "t487": "1", "w487": "seria", "t488": "1", "w488": "colmo", "t489": "1", "w489": "trabajaras", "t490": "1", "w490": "logro", "t491": "1", "w491": "mediocre", "t492": "1", "w492": "despistaje", "t493": "1", "w493": "horizonte", "t494": "1", "w494": "falsa", "t495": "1", "w495": "analisis", "t496": "1", "w496": "tania", "t497": "1", "w497": "rojas", "t498": "1", "w498": "economista", "t499": "1", "w499": "investigadora", "t500": "1", "w500": "fallo", "t501": "1", "w501": "suicidio", "t502": "1", "w502": "colectivo", "t503": "1", "w503": "normalidad", "t504": "1", "w504": "ag\u00fcito", "t505": "1", "w505": "solos", "t506": "1", "w506": "particula", "t507": "1", "w507": "humedad", "t508": "1", "w508": "paz", "t509": "1", "w509": "pendejo", "t510": "1", "w510": "madre", "t511": "1", "w511": "energia", "t512": "1", "w512": "elecciones", "t513": "1", "w513": "democraticas", "t514": "1", "w514": "periodos", "t515": "1", "w515": "linea", "t516": "1", "w516": "servicio", "t517": "1", "w517": "fletes", "t518": "1", "w518": "mudanzas", "t519": "1", "w519": "locales", "t520": "1", "w520": "foraneos", "t521": "1", "w521": "correspondientes", "t522": "1", "w522": "base", "t523": "1", "w523": "cotizacion", "t524": "1", "w524": "whats", "t525": "1", "w525": "examenes", "t526": "1", "w526": "finales", "t527": "1", "w527": "pedo", "t528": "1", "w528": "gripa", "t529": "1", "w529": "salida", "t530": "1", "w530": "negativas", "t531": "1", "w531": "antigenos", "t532": "1", "w532": "cierto", "t533": "1", "w533": "chicos", "t534": "1", "w534": "manera", "t535": "1", "w535": "puntual", "t536": "1", "w536": "momentos", "t537": "1", "w537": "realizacion", "t538": "1", "w538": "masiva", "t539": "1", "w539": "oxigeno", "t540": "1", "w540": "domicilio", "t541": "1", "w541": "entrega", "t542": "1", "w542": "medicamentos", "t543": "1", "w543": "seguimiento", "t544": "1", "w544": "medico", "t545": "1", "w545": "exitoso", "t546": "1", "w546": "plan", "t547": "1", "w547": "nmmsss", "t548": "1", "w548": "estadistica", "t549": "1", "w549": "mental", "t550": "1", "w550": "profe", "t551": "1", "w551": "sacos", "t552": "1", "w552": "encuestas", "t553": "1", "w553": "invitacion", "t554": "1", "w554": "libro", "t555": "1", "w555": "traigo", "t556": "1", "w556": "come", "t557": "1", "w557": "carne", "t558": "1", "w558": "esquema", "t559": "1", "w559": "unidad", "t560": "1", "w560": "deportiva", "t561": "1", "w561": "federales", "t562": "1", "w562": "poder", "t563": "1", "w563": "unica", "t564": "1", "w564": "citas", "t565": "1", "w565": "traves", "t566": "1", "w566": "coyotes", "t567": "1", "w567": "obviamente", "t568": "1", "w568": "enemigo", "t569": "1", "w569": "preguntales", "t570": "1", "w570": "baja", "t571": "1", "w571": "afluencia", "t572": "1", "w572": "modulo", "t573": "1", "w573": "ciudad", "t574": "1", "w574": "universitaria", "t575": "1", "w575": "mayores", "t576": "1", "w576": "rezago", "t577": "1", "w577": "hrs", "t578": "1", "w578": "novio", "t579": "1", "w579": "aaah", "t580": "1", "w580": "asi", "t581": "1", "w581": "migrante", "t582": "1", "w582": "\ud83d\udc8a", "t583": "1", "w583": "internacional", "t584": "1", "w584": "medicines", "t585": "1", "w585": "chiapas", "t586": "1", "w586": "pasado", "t587": "1", "w587": "plena", "t588": "1", "w588": "intente", "t589": "1", "w589": "aprendermelo", "t590": "1", "w590": "\ud83d\udce2", "t591": "1", "w591": "momento", "t592": "1", "w592": "sad", "t593": "1", "w593": "anterior", "t594": "1", "w594": "foto", "t595": "1", "w595": "pense", "t596": "1", "w596": "regalo", "t597": "1", "w597": "\ud83d\udcad", "t598": "1", "w598": "sabias", "t599": "1", "w599": "dentistas", "t600": "1", "w600": "protocolo", "t601": "1", "w601": "infecciones", "t602": "1", "w602": "estricto", "t603": "1", "w603": "cambios", "t604": "1", "w604": "citopaticos", "t605": "1", "w605": "papiloma", "t606": "1", "w606": "humano", "t607": "1", "w607": "coilocitos", "t608": "1", "w608": "\ud83e\udd74", "t609": "1", "w609": "completa", "t610": "1", "w610": "tonteria", "t611": "1", "w611": "controlada", "t612": "1", "w612": "decesos", "t613": "1", "w613": "alcohol", "t614": "1", "w614": "lumbre", "t615": "1", "w615": "corte", "t616": "1", "w616": "hospitalizaciones", "t617": "1", "w617": "intubadas", "t618": "1", "w618": "bienestar", "t619": "1", "w619": "socioemocional", "t620": "1", "w620": "estudiantes", "t621": "1", "w621": "docentes", "t622": "1", "w622": "distancia", "t623": "1", "w623": "contexto", "t624": "1", "w624": "on", "t625": "1", "w625": "cruise", "t626": "1", "w626": "ship", "t627": "1", "w627": "but", "t628": "1", "w628": "montezuma\u2019s", "t629": "1", "w629": "recuerdo", "t630": "1", "w630": "vuelta", "t631": "1", "w631": "tequila", "t632": "1", "w632": "previo", "t633": "1", "w633": "bomba", "t634": "1", "w634": "fragmento", "t635": "1", "w635": "avance", "t636": "1", "w636": "noticias", "t637": "1", "w637": "pulso", "t638": "1", "w638": "vespertino", "t639": "1", "w639": "radio", "t640": "1", "w640": "covid", "t641": "1", "w641": "negativo", "t642": "1", "w642": "habia", "t643": "1", "w643": "florida", "t644": "1", "w644": "cancer", "t645": "1", "w645": "mama", "t646": "1", "w646": "etapa", "t647": "1", "w647": "cronica", "t648": "1", "w648": "desastre", "t649": "1", "w649": "sanitario", "t650": "1", "w650": "anunciado", "t651": "1", "w651": "gente", "t652": "1", "w652": "vacunada", "t653": "1", "w653": "mascarillas", "t654": "1", "w654": "accion", "t655": "1", "w655": "vas", "t656": "1", "w656": "who", "t657": "1", "w657": "injury", "t658": "1", "w658": "minkah", "t659": "1", "w659": "duda", "t660": "1", "w660": "siguiente", "t661": "1", "w661": "juego", "t662": "1", "w662": "mundiales", "t663": "1", "w663": "farmaco", "t664": "1", "w664": "estaria", "t665": "1", "w665": "beneficiaria", "t666": "1", "w666": "ayuntamiento", "t667": "1", "w667": "actividades", "t668": "1", "w668": "siquiera", "t669": "1", "w669": "existencia", "t670": "1", "w670": "necesidad", "t671": "1", "w671": "larga", "t672": "1", "w672": "software", "t673": "1", "w673": "libre", "t674": "1", "w674": "trailer", "t675": "1", "w675": "diciembre", "t676": "1", "w676": "mediante", "t677": "1", "w677": "teniamos", "t678": "1", "w678": "buenas", "t679": "1", "w679": "rotaciones", "t680": "1", "w680": "previas", "t681": "1", "w681": "negras", "t682": "1", "w682": "ahi", "t683": "1", "w683": "nuevo", "t684": "1", "w684": "ropa", "t685": "1", "w685": "solucion", "t686": "1", "w686": "corto", "t687": "1", "w687": "plazo", "t688": "1", "w688": "agudizo", "t689": "1", "w689": "necesitadas", "t690": "1", "w690": "post", "t691": "1", "w691": "campa\u00f1a", "t692": "1", "w692": "realidad", "t693": "1", "w693": "integracion", "t694": "1", "w694": "social", "t695": "1", "w695": "2006", "t696": "1", "w696": "sistema", "t697": "1", "w697": "contagio", "t698": "1", "w698": "oido", "t699": "1", "w699": "tapados", "t700": "1", "w700": "sierra", "t701": "1", "w701": "ejercicio", "t702": "1", "w702": "saludos", "t703": "1", "w703": "cabo", "t704": "1", "w704": "reunion", "t705": "1", "w705": "ultimos", "t706": "1", "w706": "indicadores", "t707": "1", "w707": "economica", "t708": "1", "w708": "tio", "t709": "1", "w709": "malito", "t710": "1", "w710": "donadores", "t711": "1", "w711": "plasma", "t712": "1", "w712": "minimo", "t713": "1", "w713": "agradeceria", "t714": "1", "w714": "mejorare", "t715": "1", "w715": "pulmonia", "t716": "1", "w716": "animo", "t717": "1", "w717": "emergencia", "t718": "1", "w718": "paxlovid", "t719": "1", "w719": "riesgo", "t720": "1", "w720": "hospitalizacion", "t721": "1", "w721": "respiratorios", "t722": "1", "w722": "asistio", "t723": "1", "w723": "palnorte", "t724": "1", "w724": "cuenta", "t725": "1", "w725": "nada", "t726": "1", "w726": "cheve", "t727": "1", "w727": "anal", "t728": "1", "w728": "situacion", "t729": "1", "w729": "doble", "t730": "1", "w730": "moralista", "t731": "1", "w731": "identidad", "t732": "1", "w732": "estudiante", "t733": "1", "w733": "contagiado", "t734": "1", "w734": "nombre", "t735": "1", "w735": "dispuesto", "t736": "1", "w736": "posada", "t737": "1", "w737": "colegas", "t738": "1", "w738": "mortandad", "t739": "1", "w739": "efectos", "t740": "1", "w740": "secundarios", "t741": "1", "w741": "adversos", "t742": "1", "w742": "ex", "t743": "1", "w743": "pareja", "t744": "1", "w744": "sano", "t745": "1", "w745": "comentario", "t746": "1", "w746": "temor", "t747": "1", "w747": "mexiquenses", "t748": "1", "w748": "juicios", "t749": "1", "w749": "amparo", "t750": "1", "w750": "2019", "t751": "1", "w751": "orden", "t752": "1", "w752": "\ud83d\ude06", "t753": "1", "w753": "evidencia", "t754": "1", "w754": "cannabinoides", "t755": "1", "w755": "trastornos", "t756": "1", "w756": "depresivos", "t757": "1", "w757": "deficit", "t758": "1", "w758": "hiperactividad", "t759": "1", "w759": "tourette", "t760": "1", "w760": "tept", "t761": "1", "w761": "psicosis", "t762": "1", "w762": "lancet", "t763": "1", "w763": "psychiatry", "t764": "1", "w764": "mando", "t765": "1", "w765": "tecito", "t766": "1", "w766": "it\u2019s", "t767": "1", "w767": "fucking", "t768": "1", "w768": "rules", "t769": "1", "w769": "cuarentena", "t770": "1", "w770": "\ud83d\ude13", "t771": "1", "w771": "respuestas", "t772": "1", "w772": "nivel", "t773": "1", "w773": "economico", "t774": "1", "w774": "jajajajaja", "t775": "1", "w775": "puras", "t776": "1", "w776": "mentiras", "t777": "1", "w777": "deberias", "t778": "1", "w778": "vehemencia", "t779": "1", "w779": "politico", "t780": "1", "w780": "ciencia", "t781": "1", "w781": "plano", "t782": "1", "w782": "noviembre.", "t783": "1", "w783": "\ud83e\udda0", "t784": "1", "w784": "ultimas", "t785": "1", "w785": "horas", "t786": "1", "w786": "lamentables", "t787": "1", "w787": "coronavirus", "t788": "1", "w788": "estatal", "t789": "1", "w789": "\ud83d\udc47", "t790": "1", "w790": "aspirate", "t791": "1", "w791": "injection", "t792": "1", "w792": "lol", "t793": "1", "w793": "detectables", "t794": "1", "w794": "ags", "t795": "1", "w795": "positivo", "t796": "1", "w796": "meseta", "t797": "1", "w797": "computadora", "t798": "1", "w798": "hachazos", "t799": "1", "w799": "\ud83d\udd34", "t800": "1", "w800": "disminucion", "t801": "1", "w801": "\u270d", "t802": "1", "w802": "andres", "t803": "1", "w803": "noche", "t804": "1", "w804": "nacional", "t805": "1", "w805": "sana", "t806": "1", "w806": "do\u00f1a", "t807": "1", "w807": "inoculaciones", "t808": "1", "w808": "raquitica", "t809": "1", "w809": "peque\u00f1o", "t810": "1", "w810": "reino", "t811": "1", "w811": "agorera", "t812": "1", "w812": "fuckin", "t813": "1", "w813": "man", "t814": "1", "w814": "pertenecientes", "t815": "1", "w815": "refuerzo", "t816": "1", "w816": "detalles", "t817": "1", "w817": "ajajajajaj", "t818": "1", "w818": "bellas", "t819": "1", "w819": "memorias", "t820": "1", "w820": "oscuros", "t821": "1", "w821": "salinas", "t822": "1", "w822": "cumplimiento", "t823": "1", "w823": "amparos", "t824": "1", "w824": "promovidos", "t825": "1", "w825": "indecisos", "t826": "1", "w826": "animense", "t827": "1", "w827": "\ud83c\udfb7", "t828": "1", "w828": "exceso", "t829": "1", "w829": "mortalidad", "t830": "1", "w830": "reporto", "t831": "1", "w831": "muertes", "t832": "1", "w832": "defuncion", "t833": "1", "w833": "office", "t834": "1", "w834": "\ud83d\ude1e", "t835": "1", "w835": "gripe"}]}